{"version": 0.6, "generator": "Overpass API 0.7.62.1 084b4234", "osm3s": {"timestamp_osm_base": "2024-04-26T23:31:24Z", "copyright": "The data included in this document is from www.openstreetmap.org. The data is made available under ODbL."}, "elements": [{"type": "node", "id": 3701202274, "lat": 25.0688653, "lon": 92.3787654, "tags": {"name": "Forest resthouse", "tourism": "guest_house"}}, {"type": "node", "id": 7018603486, "lat": 25.1533539, "lon": 92.3667986, "tags": {"name": "Masun Hotel", "tourism": "hotel"}}, {"type": "node", "id": 7018603487, "lat": 25.1125738, "lon": 92.3678015, "tags": {"name": "Mini Hotel", "name:en": "Mini hotel", "phone": "9774485583", "tourism": "hotel"}}]}