{"version": 0.6, "generator": "Overpass API 0.7.62.1 084b4234", "osm3s": {"timestamp_osm_base": "2024-04-27T01:32:05Z", "copyright": "The data included in this document is from www.openstreetmap.org. The data is made available under ODbL."}, "elements": [{"type": "node", "id": 560819470, "lat": 36.898378, "lon": 7.7578958, "tags": {"tourism": "hotel"}}, {"type": "node", "id": 560819472, "lat": 36.8976667, "lon": 7.757752, "tags": {"tourism": "hotel"}}, {"type": "node", "id": 560820603, "lat": 36.8963564, "lon": 7.7576429, "tags": {"tourism": "hotel"}}, {"type": "node", "id": 1212005075, "lat": 36.9137134, "lon": 7.7503395, "tags": {"name": "Imara R\u00e9sidence (ex-Chateau Chancel)", "tourism": "hotel"}}, {"type": "node", "id": 1212053243, "lat": 36.9380986, "lon": 7.7672911}, {"type": "node", "id": 1212053256, "lat": 36.9479969, "lon": 7.7723269, "tags": {"name": "Rym El Djamil", "tourism": "hotel"}}, {"type": "node", "id": 1771309629, "lat": 36.9039504, "lon": 7.760783}, {"type": "node", "id": 1771309630, "lat": 36.9039332, "lon": 7.7613144}, {"type": "node", "id": 1771309631, "lat": 36.9037987, "lon": 7.7613213}, {"type": "node", "id": 1771309633, "lat": 36.9037398, "lon": 7.7607941}, {"type": "node", "id": 2883925204, "lat": 36.8056023, "lon": 7.734683}, {"type": "node", "id": 2883925209, "lat": 36.8057175, "lon": 7.7342755}, {"type": "node", "id": 2883925210, "lat": 36.8058285, "lon": 7.7347827}, {"type": "node", "id": 2883925212, "lat": 36.8059436, "lon": 7.7343752}, {"type": "node", "id": 3365284122, "lat": 36.9038004, "lon": 7.7613726}, {"type": "node", "id": 3365284149, "lat": 36.9039349, "lon": 7.7613656}, {"type": "node", "id": 3365284182, "lat": 36.9039682, "lon": 7.7613125}, {"type": "node", "id": 3365284309, "lat": 36.9037576, "lon": 7.7613235}, {"type": "node", "id": 3367344471, "lat": 36.8977273, "lon": 7.7367921}, {"type": "node", "id": 3367344481, "lat": 36.8978734, "lon": 7.7371605}, {"type": "node", "id": 3367349803, "lat": 36.8977785, "lon": 7.7371778}, {"type": "node", "id": 3367349814, "lat": 36.8978209, "lon": 7.7367756}, {"type": "node", "id": 3467691289, "lat": 36.8731011, "lon": 7.7168226}, {"type": "node", "id": 3467691290, "lat": 36.8741319, "lon": 7.7157434}, {"type": "node", "id": 3467691291, "lat": 36.8746581, "lon": 7.7151764}, {"type": "node", "id": 3467691292, "lat": 36.8751571, "lon": 7.714678}, {"type": "node", "id": 3467692693, "lat": 36.8753343, "lon": 7.7144972}, {"type": "node", "id": 3467692694, "lat": 36.8755582, "lon": 7.7142874}, {"type": "node", "id": 3467692695, "lat": 36.8755045, "lon": 7.7140688}, {"type": "node", "id": 3467692696, "lat": 36.8754836, "lon": 7.7138968}, {"type": "node", "id": 3467692697, "lat": 36.8754346, "lon": 7.713751}, {"type": "node", "id": 3467692698, "lat": 36.8753711, "lon": 7.7136373}, {"type": "node", "id": 3467692699, "lat": 36.8752366, "lon": 7.7135263}, {"type": "node", "id": 3467692700, "lat": 36.8751731, "lon": 7.7134723}, {"type": "node", "id": 3467692701, "lat": 36.8751048, "lon": 7.7134199}, {"type": "node", "id": 3467692702, "lat": 36.8751335, "lon": 7.7130483}, {"type": "node", "id": 3467692703, "lat": 36.8750496, "lon": 7.7128445}, {"type": "node", "id": 3467692704, "lat": 36.8737194, "lon": 7.7127648}, {"type": "node", "id": 3467692705, "lat": 36.8729235, "lon": 7.7125452}, {"type": "node", "id": 3467692706, "lat": 36.8727011, "lon": 7.7124106}, {"type": "node", "id": 3467692707, "lat": 36.872258, "lon": 7.7119821}, {"type": "node", "id": 3467692708, "lat": 36.8724018, "lon": 7.7125963}, {"type": "node", "id": 3467692709, "lat": 36.8723565, "lon": 7.7151592}, {"type": "node", "id": 3467692710, "lat": 36.8726514, "lon": 7.716487}, {"type": "node", "id": 3467692711, "lat": 36.8729266, "lon": 7.7163355}, {"type": "node", "id": 3467692712, "lat": 36.8738057, "lon": 7.7124354}, {"type": "node", "id": 3467692713, "lat": 36.8738104, "lon": 7.7123664}, {"type": "node", "id": 3467692714, "lat": 36.8748667, "lon": 7.7126229}, {"type": "node", "id": 3790232892, "lat": 36.8820339, "lon": 7.7517817, "tags": {"name": "Mus\u00e9e des Ruines d'Hippone", "name:ar": "\u0645\u062a\u062d\u0641 \u0647\u064a\u0628\u0648\u0646", "name:fr": "Mus\u00e9e des Ruines d'Hippone", "tourism": "museum"}}, {"type": "node", "id": 3812922610, "lat": 36.9017073, "lon": 7.7611391}, {"type": "node", "id": 3812922611, "lat": 36.9023687, "lon": 7.7610958}, {"type": "node", "id": 3812922612, "lat": 36.9026152, "lon": 7.7613922}, {"type": "node", "id": 3812922613, "lat": 36.9031751, "lon": 7.7614319}, {"type": "node", "id": 3812922614, "lat": 36.9032435, "lon": 7.7620867}, {"type": "node", "id": 3812922615, "lat": 36.9037182, "lon": 7.7629379}, {"type": "node", "id": 3812922616, "lat": 36.9037525, "lon": 7.7632812}, {"type": "node", "id": 3812922617, "lat": 36.9029031, "lon": 7.7635602}, {"type": "node", "id": 3812922618, "lat": 36.9022597, "lon": 7.7638928}, {"type": "node", "id": 3812922619, "lat": 36.9015846, "lon": 7.7615161}, {"type": "node", "id": 4016238226, "lat": 36.9450354, "lon": 7.7633189, "tags": {"name": "Motel Nassim", "tourism": "motel", "wheelchair": "yes"}}, {"type": "node", "id": 4016238244, "lat": 36.9455976, "lon": 7.7695064, "tags": {"name": "belles vues d'air", "tourism": "viewpoint"}}, {"type": "node", "id": 4016238344, "lat": 36.9490816, "lon": 7.7746089, "tags": {"tourism": "viewpoint"}}, {"type": "node", "id": 4016238445, "lat": 36.9663967, "lon": 7.7829473, "tags": {"tourism": "viewpoint"}}, {"type": "node", "id": 4016603234, "lat": 36.9361375, "lon": 7.7670705, "tags": {"tourism": "viewpoint"}}, {"type": "node", "id": 4016603278, "lat": 36.9350912, "lon": 7.7663056, "tags": {"tourism": "viewpoint"}}, {"type": "node", "id": 4100396192, "lat": 36.7570729, "lon": 7.7415063, "tags": {"addr:street": "\u0627\u0644\u0637\u0631\u064a\u0642 \u0627\u0644\u0648\u0637\u0646\u064a \u0631\u0642\u0645 16", "name": "\u0645\u0633\u062c\u062f \u0627\u0644\u0647\u062f\u0649", "name:ar": "\u0645\u0633\u062c\u062f \u0627\u0644\u0647\u062f\u0649", "name:fr": "Masdj al houda", "opening_hours": "24/7", "tourism": "museum"}}, {"type": "node", "id": 4138335191, "lat": 36.9554498, "lon": 7.7783204, "tags": {"tourism": "picnic_site"}}, {"type": "node", "id": 4212532574, "lat": 36.8225012, "lon": 7.7192467, "tags": {"addr:city": "Sidi Amar", "addr:postcode": "23005", "tourism": "hotel"}}, {"type": "node", "id": 4232925332, "lat": 36.9599059, "lon": 7.7808481}, {"type": "node", "id": 4232925333, "lat": 36.9599408, "lon": 7.7807371}, {"type": "node", "id": 4232925334, "lat": 36.9597039, "lon": 7.7806243}, {"type": "node", "id": 4232925335, "lat": 36.9596384, "lon": 7.7806225}, {"type": "node", "id": 4232925336, "lat": 36.959464, "lon": 7.7805788}, {"type": "node", "id": 4232925337, "lat": 36.9593564, "lon": 7.7805352}, {"type": "node", "id": 4232925338, "lat": 36.9592736, "lon": 7.780446}, {"type": "node", "id": 4232925339, "lat": 36.9592052, "lon": 7.7802732}, {"type": "node", "id": 4232925340, "lat": 36.9590947, "lon": 7.7799948}, {"type": "node", "id": 4232925341, "lat": 36.9589988, "lon": 7.7797765}, {"type": "node", "id": 4232925342, "lat": 36.9589246, "lon": 7.7796273}, {"type": "node", "id": 4232925343, "lat": 36.9587313, "lon": 7.7793744}, {"type": "node", "id": 4232925344, "lat": 36.9586077, "lon": 7.7792616}, {"type": "node", "id": 4232925345, "lat": 36.9585379, "lon": 7.7792089}, {"type": "node", "id": 4232925346, "lat": 36.958458, "lon": 7.7791961}, {"type": "node", "id": 4232925347, "lat": 36.9584464, "lon": 7.7792252}, {"type": "node", "id": 4232925348, "lat": 36.9584231, "lon": 7.779369}, {"type": "node", "id": 4232925349, "lat": 36.9584318, "lon": 7.7796473}, {"type": "node", "id": 4232925350, "lat": 36.958474, "lon": 7.7799675}, {"type": "node", "id": 4232925351, "lat": 36.9583548, "lon": 7.7800676}, {"type": "node", "id": 4232925352, "lat": 36.9584027, "lon": 7.7801549}, {"type": "node", "id": 4232925353, "lat": 36.9584856, "lon": 7.7802222}, {"type": "node", "id": 4232925354, "lat": 36.9585423, "lon": 7.7803587}, {"type": "node", "id": 4232925355, "lat": 36.9585743, "lon": 7.7805588}, {"type": "node", "id": 4232925356, "lat": 36.9586819, "lon": 7.780799}, {"type": "node", "id": 4232925357, "lat": 36.958788, "lon": 7.7808299}, {"type": "node", "id": 4232925358, "lat": 36.9588083, "lon": 7.7809391}, {"type": "node", "id": 4232925359, "lat": 36.9589246, "lon": 7.7811155}, {"type": "node", "id": 4232925360, "lat": 36.9591224, "lon": 7.7813466}, {"type": "node", "id": 4232925361, "lat": 36.959166, "lon": 7.7813866}, {"type": "node", "id": 4232925362, "lat": 36.959528, "lon": 7.7811446}, {"type": "node", "id": 4235893267, "lat": 37.0569464, "lon": 7.3863734}, {"type": "node", "id": 4250811342, "lat": 37.0570957, "lon": 7.3864335}, {"type": "node", "id": 4250811343, "lat": 37.0573453, "lon": 7.3854627}, {"type": "node", "id": 4250811347, "lat": 37.0564292, "lon": 7.3860822}, {"type": "node", "id": 4250811348, "lat": 37.0563949, "lon": 7.386152}, {"type": "node", "id": 4259470995, "lat": 36.9163084, "lon": 7.6719625}, {"type": "node", "id": 4259470996, "lat": 36.9163608, "lon": 7.6717769}, {"type": "node", "id": 4259470997, "lat": 36.9164742, "lon": 7.6718079}, {"type": "node", "id": 4259470998, "lat": 36.9165702, "lon": 7.6718479}, {"type": "node", "id": 4259470999, "lat": 36.9166429, "lon": 7.6718715}, {"type": "node", "id": 4259471000, "lat": 36.916707, "lon": 7.6719152}, {"type": "node", "id": 4259471001, "lat": 36.9167753, "lon": 7.6720044}, {"type": "node", "id": 4259471002, "lat": 36.9168073, "lon": 7.6720608}, {"type": "node", "id": 4259471003, "lat": 36.9168117, "lon": 7.6720826}, {"type": "node", "id": 4259471004, "lat": 36.9168408, "lon": 7.6720644}, {"type": "node", "id": 4259471005, "lat": 36.9168335, "lon": 7.6719989}, {"type": "node", "id": 4259471006, "lat": 36.9168466, "lon": 7.6719498}, {"type": "node", "id": 4259471007, "lat": 36.916896, "lon": 7.6719207}, {"type": "node", "id": 4259471008, "lat": 36.9169368, "lon": 7.6719334}, {"type": "node", "id": 4259471009, "lat": 36.9169731, "lon": 7.6719898}, {"type": "node", "id": 4259471010, "lat": 36.917011, "lon": 7.6720808}, {"type": "node", "id": 4259471011, "lat": 36.917011, "lon": 7.6721608}, {"type": "node", "id": 4259471012, "lat": 36.916979, "lon": 7.6722118}, {"type": "node", "id": 4259471013, "lat": 36.9169426, "lon": 7.6722318}, {"type": "node", "id": 4259471014, "lat": 36.9168929, "lon": 7.6722016}, {"type": "node", "id": 4259471015, "lat": 36.916864, "lon": 7.6721372}, {"type": "node", "id": 4259471016, "lat": 36.9168364, "lon": 7.6721444}, {"type": "node", "id": 4259471017, "lat": 36.9168175, "lon": 7.6721772}, {"type": "node", "id": 4259471018, "lat": 36.9168306, "lon": 7.6722918}, {"type": "node", "id": 4259471019, "lat": 36.9168131, "lon": 7.6724283}, {"type": "node", "id": 4259471020, "lat": 36.9167608, "lon": 7.6725611}, {"type": "node", "id": 4259471021, "lat": 36.916688, "lon": 7.6726812}, {"type": "node", "id": 4259471022, "lat": 36.9165877, "lon": 7.6727849}, {"type": "node", "id": 4259471023, "lat": 36.9164844, "lon": 7.6728867}, {"type": "node", "id": 4259471024, "lat": 36.9164029, "lon": 7.6729723}, {"type": "node", "id": 4259471025, "lat": 36.9162444, "lon": 7.6727248}, {"type": "node", "id": 4259471026, "lat": 36.9163724, "lon": 7.6725647}, {"type": "node", "id": 4259471027, "lat": 36.9164262, "lon": 7.6726684}, {"type": "node", "id": 4259471028, "lat": 36.9164946, "lon": 7.6726775}, {"type": "node", "id": 4259471029, "lat": 36.9165149, "lon": 7.6726211}, {"type": "node", "id": 4259471030, "lat": 36.9164684, "lon": 7.6725702}, {"type": "node", "id": 4259471031, "lat": 36.9165135, "lon": 7.6724519}, {"type": "node", "id": 4259471032, "lat": 36.9165453, "lon": 7.6723937}, {"type": "node", "id": 4259471033, "lat": 36.9165848, "lon": 7.6723391}, {"type": "node", "id": 4259471034, "lat": 36.9164277, "lon": 7.6721845}, {"type": "node", "id": 4259471035, "lat": 36.9163986, "lon": 7.6722136}, {"type": "node", "id": 4259471036, "lat": 36.9162968, "lon": 7.6720626}, {"type": "node", "id": 4259471037, "lat": 36.9162953, "lon": 7.6720007}, {"type": "node", "id": 4259471038, "lat": 36.9165244, "lon": 7.6721736}, {"type": "node", "id": 4259471039, "lat": 36.9165699, "lon": 7.6722336}, {"type": "node", "id": 4259471040, "lat": 36.916586, "lon": 7.6722864}, {"type": "node", "id": 4259471041, "lat": 36.9164935, "lon": 7.6721681}, {"type": "node", "id": 4271867440, "lat": 36.9059627, "lon": 7.7598285}, {"type": "node", "id": 4271867441, "lat": 36.9057666, "lon": 7.75983}, {"type": "node", "id": 4271867442, "lat": 36.9057684, "lon": 7.7602176}, {"type": "node", "id": 4271867443, "lat": 36.9059645, "lon": 7.7602162}, {"type": "node", "id": 4272368289, "lat": 36.8991839, "lon": 7.7599759, "tags": {"addr:street": "Cours de la r\u00e9volution", "name": "Hotel d'orient", "name:ar": "\u0641\u0646\u062f\u0642 \u0627\u0644\u0634\u0631\u0642", "name:fr": "Hotel l'Orient", "tourism": "hotel"}}, {"type": "node", "id": 4365277391, "lat": 36.9432829, "lon": 7.7675652, "tags": {"tourism": "chalet"}}, {"type": "node", "id": 4458515391, "lat": 36.9629186, "lon": 7.7866579, "tags": {"name": "Chem's", "name:ar": "Chem's", "tourism": "hotel"}}, {"type": "node", "id": 4469207190, "lat": 36.818519, "lon": 7.7119515, "tags": {"name": "\u0628\u062f\u0631\u064a \u0627\u0644\u0645\u0628\u0631\u064a", "name:ar": "\u0628\u062f\u0631\u064a \u0627\u0644\u0645\u0628\u0631\u064a", "name:fr": "Badri Al-Mubri", "tourism": "camp_site"}}, {"type": "node", "id": 4504225890, "lat": 36.7069483, "lon": 7.8501119, "tags": {"addr:city": "Besbes", "addr:country": "DZ", "name": "Alimentation g\u00e9n\u00e9rale faycal", "shop": "convenience", "tourism": "camp_site"}}, {"type": "node", "id": 4602427597, "lat": 36.830255, "lon": 7.7226467, "tags": {"name": "Cite 800 log chahmi", "name:fr": "Cite 800 log chahmi", "tourism": "attraction"}}, {"type": "node", "id": 4675017010, "lat": 36.8744436, "lon": 7.7166766, "tags": {"addr:city": "\u0639\u0646\u0627\u0628\u0629", "addr:city:ar": "\u0639\u0646\u0627\u0628\u0629", "name": "\u0645\u064a\u0645\u0648\u0632\u0627", "name:ar": "\u0645\u064a\u0645\u0648\u0632\u0627", "name:fr": "Mimosa", "tourism": "hotel"}}, {"type": "node", "id": 4744540029, "lat": 36.9128252, "lon": 7.6735795, "tags": {"name:fr": "placette de seraidi", "tourism": "artwork"}}, {"type": "node", "id": 4756688941, "lat": 36.9726104, "lon": 7.6815086, "tags": {"tourism": "attraction"}}, {"type": "node", "id": 4756738428, "lat": 37.0409703, "lon": 7.4250843, "tags": {"tourism": "attraction"}}, {"type": "node", "id": 4756743126, "lat": 37.0410227, "lon": 7.4266151, "tags": {"tourism": "attraction"}}, {"type": "node", "id": 4756744326, "lat": 37.0549532, "lon": 7.3901071, "tags": {"tourism": "attraction"}}, {"type": "node", "id": 4767094221, "lat": 36.8198117, "lon": 7.7113975, "tags": {"name": "\u0645\u062d\u0644 \u0645\u0631\u064a\u0631", "name:ar": "\u0645\u062d\u0644 \u0645\u0631\u064a\u0631", "name:fr": "Marir", "tourism": "chalet"}}, {"type": "node", "id": 4816418124, "lat": 36.8879349, "lon": 7.7460503, "tags": {"name:fr": "Maison de jeunesse", "tourism": "hostel"}}, {"type": "node", "id": 4881942728, "lat": 36.895621, "lon": 7.7216938, "tags": {"name:fr": "Meriboute", "tourism": "hotel"}}, {"type": "node", "id": 4947429821, "lat": 36.9002883, "lon": 7.7523445, "tags": {"name:fr": "Maraignan", "tourism": "hotel"}}, {"type": "node", "id": 4947429822, "lat": 36.9004415, "lon": 7.7526419, "tags": {"internet_access": "wlan", "name:fr": "H\u00f4tel maraignan", "tourism": "hotel"}}, {"type": "node", "id": 5042049223, "lat": 36.8995045, "lon": 7.7620201, "tags": {"name": "H\u00f4tel Safsaf", "name:fr": "SafSaf", "tourism": "hotel"}}, {"type": "node", "id": 5128509525, "lat": 36.8915786, "lon": 7.7280283, "tags": {"name": "Risidance el hana", "name:ar": "Risidance el hana", "tourism": "attraction"}}, {"type": "node", "id": 5216312921, "lat": 36.899712, "lon": 7.7636118, "tags": {"addr:city": "\u0639\u0646\u0627\u0628\u0629", "addr:city:ar": "\u0639\u0646\u0627\u0628\u0629", "name": "\u0641\u0646\u062f\u0642 \u0627\u0644\u0647\u0646\u0627", "name:ar": "\u0641\u0646\u062f\u0642 \u0627\u0644\u0647\u0646\u0627", "name:en": "H\u00f4tel el hana", "tourism": "hotel"}}, {"type": "node", "id": 5321704521, "lat": 36.86177, "lon": 7.7433872, "tags": {"name": "\u0627\u0644\u0645\u062c\u0645\u0648\u0639\u0629 \u0627\u0644\u0627\u0642\u0644\u064a\u0645\u064a\u0629 \u0644\u0644\u062f\u0631\u0643 \u0627\u0644\u0648\u0637\u0646\u064a \u0627\u0644\u062c\u062f\u064a\u062f\u0629", "name:ar": "\u0627\u0644\u0645\u062c\u0645\u0648\u0639\u0629 \u0627\u0644\u0627\u0642\u0644\u064a\u0645\u064a\u0629 \u0644\u0644\u062f\u0631\u0643 \u0627\u0644\u0648\u0637\u0646\u064a \u0627\u0644\u062c\u062f\u064a\u062f\u0629", "name:fr": "La nouvelle groupement gendarmerie nationale Annaba", "tourism": "artwork"}}, {"type": "node", "id": 5376722522, "lat": 36.6551393, "lon": 7.5923038, "tags": {"name": "H\u00f4tel Essalam", "tourism": "hotel"}}, {"type": "node", "id": 5516955022, "lat": 36.9016105, "lon": 7.7613293}, {"type": "node", "id": 5516955023, "lat": 36.9017321, "lon": 7.7621344}, {"type": "node", "id": 5516955024, "lat": 36.9017568, "lon": 7.7621572}, {"type": "node", "id": 5516955025, "lat": 36.9020132, "lon": 7.7630157}, {"type": "node", "id": 5516955026, "lat": 36.9019794, "lon": 7.7630085}, {"type": "node", "id": 5795798855, "lat": 36.9114038, "lon": 7.6732934, "tags": {"name": "PTT", "tourism": "hostel"}}, {"type": "node", "id": 5795837253, "lat": 36.912657, "lon": 7.679738, "tags": {"name": "PTT", "tourism": "hostel"}}, {"type": "node", "id": 5839961678, "lat": 36.9381928, "lon": 7.7672829}, {"type": "node", "id": 5839961679, "lat": 36.9382481, "lon": 7.7672179}, {"type": "node", "id": 5839961680, "lat": 36.9382546, "lon": 7.7671813}, {"type": "node", "id": 5839961681, "lat": 36.9383455, "lon": 7.7671122}, {"type": "node", "id": 5839961682, "lat": 36.9385243, "lon": 7.767104}, {"type": "node", "id": 5839961683, "lat": 36.9385243, "lon": 7.7671447}, {"type": "node", "id": 5839961684, "lat": 36.9387355, "lon": 7.7672301}, {"type": "node", "id": 5839961985, "lat": 36.9388752, "lon": 7.7670796}, {"type": "node", "id": 5839961986, "lat": 36.9387713, "lon": 7.7670105}, {"type": "node", "id": 5839961987, "lat": 36.9387453, "lon": 7.7669211}, {"type": "node", "id": 5839961988, "lat": 36.938911, "lon": 7.7668479}, {"type": "node", "id": 5839961989, "lat": 36.9390605, "lon": 7.766856}, {"type": "node", "id": 5839961990, "lat": 36.9391255, "lon": 7.7667496}, {"type": "node", "id": 5839961991, "lat": 36.9387583, "lon": 7.7661567}, {"type": "node", "id": 5839961992, "lat": 36.9385405, "lon": 7.7661404}, {"type": "node", "id": 5839961993, "lat": 36.9384475, "lon": 7.7660553}, {"type": "node", "id": 5839961994, "lat": 36.9382481, "lon": 7.7661492}, {"type": "node", "id": 5839961995, "lat": 36.9381902, "lon": 7.7661224}, {"type": "node", "id": 5839961996, "lat": 36.9377292, "lon": 7.766404}, {"type": "node", "id": 5839961997, "lat": 36.9378257, "lon": 7.7666556}, {"type": "node", "id": 5839961998, "lat": 36.937835, "lon": 7.7666503}, {"type": "node", "id": 5839962067, "lat": 36.9389699, "lon": 7.7661102}, {"type": "node", "id": 5839962068, "lat": 36.9389656, "lon": 7.7660977}, {"type": "node", "id": 5839962083, "lat": 36.9391878, "lon": 7.76674}, {"type": "node", "id": 5951523286, "lat": 36.9344525, "lon": 7.7617828, "tags": {"addr:postcode": "23000", "addr:street": "Plage la Caroube No 10", "email": "hotel.elamane@gmail.com", "internet_access": "wlan", "name": "\u0641\u0646\u062f\u0642 \u0627\u0644\u0627\u0645\u0627\u0646", "name:ar": "\u0641\u0646\u062f\u0642 \u0627\u0644\u0627\u0645\u0627\u0646", "name:en": "Hotel el Amane", "name:fr": "H\u00f4tel el Amane", "opening_hours": "24/7", "phone": "0560945701", "tourism": "hotel"}}, {"type": "node", "id": 6058720885, "lat": 36.912185, "lon": 7.762495, "tags": {"addr:city": "\u0639\u0646\u0627\u0628\u0629", "addr:city:ar": "\u0639\u0646\u0627\u0628\u0629", "addr:postcode": "23000", "tourism": "picnic_site"}}, {"type": "node", "id": 6072986295, "lat": 36.9654267, "lon": 7.7825599, "tags": {"tourism": "viewpoint"}}, {"type": "node", "id": 6072986315, "lat": 36.8657412, "lon": 7.7339162, "tags": {"name:fr": "Cite 400 logements", "tourism": "apartment"}}, {"type": "node", "id": 6072991988, "lat": 36.9227445, "lon": 7.763942, "tags": {"tourism": "viewpoint"}}, {"type": "node", "id": 6073008887, "lat": 36.9246428, "lon": 7.763121, "tags": {"tourism": "viewpoint"}}, {"type": "node", "id": 6073008891, "lat": 36.924136, "lon": 7.7192178, "tags": {"tourism": "viewpoint"}}, {"type": "node", "id": 6073008898, "lat": 36.8639574, "lon": 7.7295297, "tags": {"name:fr": "Cit\u00e9 police", "tourism": "apartment"}}, {"type": "node", "id": 6073010190, "lat": 36.8682458, "lon": 7.7290034, "tags": {"name:fr": "Cit\u00e9 200 logements", "tourism": "apartment"}}, {"type": "node", "id": 6252476686, "lat": 36.7922697, "lon": 7.61122, "tags": {"addr:city": "\u0633\u064a\u062f\u064a \u0639\u0645\u0627\u0631", "addr:city:ar": "\u0633\u064a\u062f\u064a \u0639\u0645\u0627\u0631", "addr:place": "\u062d\u062c\u0631 \u0627\u0644\u062f\u064a\u0633", "addr:place:ar": "\u062d\u062c\u0631 \u0627\u0644\u062f\u064a\u0633", "name": "\u0645\u0633\u062c\u062f \u0627\u0644\u0630\u0627\u0643\u0631\u064a\u0646", "name:ar": "\u0645\u0633\u062c\u062f \u0627\u0644\u0630\u0627\u0643\u0631\u064a\u0646", "name:fr": "Mosqu\u00e9e Edhakirine", "tourism": "hostel"}}, {"type": "node", "id": 6253587637, "lat": 36.7924103, "lon": 7.6109236, "tags": {"addr:city": "\u0633\u064a\u062f\u064a \u0639\u0645\u0627\u0631", "addr:city:ar": "\u0633\u064a\u062f\u064a \u0639\u0645\u0627\u0631", "addr:place": "\u062d\u062c\u0631 \u0627\u0644\u062f\u064a\u0633", "addr:place:ar": "\u062d\u062c\u0631 \u0627\u0644\u062f\u064a\u0633", "name": "\u0645\u0633\u062c\u062f \u0627\u0644\u0630\u0627\u0643\u0631\u064a\u0646", "name:ar": "\u0645\u0633\u062c\u062f \u0627\u0644\u0630\u0627\u0643\u0631\u064a\u0646", "name:fr": "Mosqu\u00e9e Edhakirine", "tourism": "chalet"}}, {"type": "node", "id": 6299033585, "lat": 36.7913446, "lon": 7.6117296, "tags": {"addr:city": "\u0633\u064a\u062f\u064a \u0639\u0645\u0627\u0631", "addr:city:ar": "\u0633\u064a\u062f\u064a \u0639\u0645\u0627\u0631", "addr:place": "\u062d\u062c\u0631 \u0627\u0644\u062f\u064a\u0633", "addr:place:ar": "\u062d\u062c\u0631 \u0627\u0644\u062f\u064a\u0633", "name": "\u0645\u0648\u0642\u0641 \u0633\u064a\u0627\u0631\u0627\u062a", "name:ar": "\u0645\u0648\u0642\u0641 \u0633\u064a\u0627\u0631\u0627\u062a", "name:fr": "Parking Auto", "tourism": "caravan_site"}}, {"type": "node", "id": 6760656185, "lat": 36.9007078, "lon": 7.7615304, "tags": {"addr:city": "\u0639\u0646\u0627\u0628\u0629", "addr:city:ar": "\u0639\u0646\u0627\u0628\u0629", "name": "\u0627\u0644\u0623\u0646\u062f\u0644\u0633", "name:ar": "\u0627\u0644\u0623\u0646\u062f\u0644\u0633", "name:en": "Elandalous", "name:fr": "Andalous", "tourism": "hotel"}}, {"type": "node", "id": 6860712985, "lat": 36.8967919, "lon": 7.7531901, "tags": {"name": "\u0645\u0631\u0642\u062f \u0633\u064a\u062f\u064a \u0627\u0628\u0631\u0627\u0647\u064a\u0645", "name:ar": "\u0645\u0631\u0642\u062f \u0633\u064a\u062f\u064a \u0627\u0628\u0631\u0627\u0647\u064a\u0645", "name:en": "Dorm Sidi Brahim", "name:fr": "Dortoir Sidi Brahim", "tourism": "motel"}}, {"type": "node", "id": 6869435894, "lat": 36.9149002, "lon": 7.7509237, "tags": {"addr:city": "\u0639\u0646\u0627\u0628\u0629", "addr:city:ar": "\u0639\u0646\u0627\u0628\u0629", "name": "\u0625\u0642\u0627\u0645\u0629 \u062c\u0646\u0627\u0646 \u0627\u0644\u0628\u0627\u064a", "name:ar": "\u0625\u0642\u0627\u0645\u0629 \u062c\u0646\u0627\u0646 \u0627\u0644\u0628\u0627\u064a", "name:en": "Djenan El-Bey residence", "name:fr": "R\u00e9sidence Djenan El-Bey", "tourism": "apartment"}}, {"type": "node", "id": 6919950085, "lat": 36.8976918, "lon": 7.7633148, "tags": {"name": "\u0627\u0644\u062f\u0627\u0626\u0631\u0629 \u0627\u0644\u0628\u062d\u0631\u064a\u0629 \u0639\u0646\u0627\u0628\u0629", "name:ar": "\u0627\u0644\u062f\u0627\u0626\u0631\u0629 \u0627\u0644\u0628\u062d\u0631\u064a\u0629 \u0639\u0646\u0627\u0628\u0629", "name:en": "Maritime district of Annaba", "name:fr": "D\u00e9partement maritime d'Annaba", "tourism": "apartment"}}, {"type": "node", "id": 7044729187, "lat": 36.7054946, "lon": 7.8381396, "tags": {"amenity": "bar", "tourism": "camp_site"}}, {"type": "node", "id": 7868339285, "lat": 36.8989191, "lon": 7.7547036, "tags": {"tourism": "picnic_site"}}, {"type": "node", "id": 7868402585, "lat": 36.9004982, "lon": 7.7520295, "tags": {"addr:street": "Boulevard Souidani Boudjemaa", "name": "\u0641\u0646\u062f\u0642 \u0627\u0644\u0631\u0634\u0631\u0627\u0634", "name:ar": "\u0641\u0646\u062f\u0642 \u0631\u0634\u0631\u0627\u0634", "name:en": "Hotel racherache", "name:fr": "H\u00f4tel Racherache", "tourism": "hotel"}}, {"type": "node", "id": 8271291766, "lat": 36.9134242, "lon": 7.7426438, "tags": {"name": "\u0645\u062a\u062d\u0641 \u0627\u0644\u0645\u062c\u0627\u0647\u062f", "tourism": "museum"}}, {"type": "node", "id": 9716395717, "lat": 36.8595492, "lon": 7.738451, "tags": {"name:fr": "A1", "tourism": "artwork"}}, {"type": "node", "id": 9716607717, "lat": 36.8599495, "lon": 7.7383812, "tags": {"name:fr": "A1", "tourism": "artwork"}}, {"type": "node", "id": 9716607917, "lat": 36.8601135, "lon": 7.7387633, "tags": {"name:fr": "A2", "tourism": "artwork"}}, {"type": "node", "id": 9716608017, "lat": 36.8602742, "lon": 7.7391595, "tags": {"name:fr": "A3", "tourism": "artwork"}}, {"type": "node", "id": 9716608117, "lat": 36.8604204, "lon": 7.7395324, "tags": {"name:fr": "A4", "tourism": "artwork"}}, {"type": "node", "id": 9716608317, "lat": 36.8605058, "lon": 7.7398468, "tags": {"name:fr": "B1", "tourism": "artwork"}}, {"type": "node", "id": 9716608417, "lat": 36.8605416, "lon": 7.7403401, "tags": {"name:fr": "B2", "tourism": "artwork"}}, {"type": "node", "id": 9827252017, "lat": 36.9031203, "lon": 7.7580993, "tags": {"addr:housenumber": "1507", "addr:postcode": "23000", "addr:street": "Val mascots", "tourism": "guest_house"}}, {"type": "node", "id": 11034491005, "lat": 36.8952958, "lon": 7.7211224, "tags": {"name:fr": "T\u00e9l\u00e9ph\u00e9rique", "tourism": "hotel"}}, {"type": "node", "id": 11034592705, "lat": 36.8750497, "lon": 7.7145724, "tags": {"name:fr": "Parc Farouk Land", "tourism": "attraction"}}, {"type": "node", "id": 11389639369, "lat": 36.9005572, "lon": 7.7573499, "tags": {"name:en": "pursiegle tour", "tourism": "apartment"}}, {"type": "node", "id": 11841902896, "lat": 36.8987735, "lon": 7.7613063, "tags": {"name": "Hostel Libert\u00e9", "tourism": "hostel"}}, {"type": "way", "id": 165582442, "nodes": [1771309629, 3365284182, 1771309630, 3365284149, 3365284122, 1771309631, 3365284309, 1771309633, 1771309629], "tags": {"addr:city": "Annaba \u0639\u0646\u0627\u0628\u0629", "addr:postcode": "23000", "addr:street": "Rue du 24 F\u00e9vrier 1956", "building": "hotel", "building:levels": "18", "name": "H\u00f4tel Seybouse International", "source": "Bing", "tourism": "hotel"}}, {"type": "way", "id": 284669569, "nodes": [2883925209, 2883925204, 2883925210, 2883925212, 2883925209], "tags": {"building": "yes", "fax": "+21338892050", "internet_access": "yes", "name": "\u0641\u0646\u062f\u0642 \u0627\u0644\u0645\u0646\u0642\u0627\u0633", "name:ar": "\u0641\u0646\u062f\u0642 \u0627\u0644\u0645\u0646\u0642\u0627\u0633", "name:en": "El-Moungas Hotel", "name:fr": "Hotel El moungas", "phone": "+21338891185", "source": "Bing", "tourism": "hotel"}}, {"type": "way", "id": 329788165, "nodes": [3367349803, 3367344481, 3367349814, 3367344471, 3367349803], "tags": {"tourism": "museum"}}, {"type": "way", "id": 339550199, "nodes": [3467691289, 3467691290, 3467691291, 3467691292, 3467692693, 3467692694, 3467692695, 3467692696, 3467692697, 3467692698, 3467692699, 3467692700, 3467692701, 3467692702, 3467692703, 3467692714, 3467692713, 3467692712, 3467692704, 3467692705, 3467692706, 3467692707, 3467692708, 3467692709, 3467692710, 3467692711, 3467691289], "tags": {"name": "Parc d'attraction Annaba", "name:ar": "\u062d\u062f\u064a\u0642\u0629 \u0627\u0644\u062a\u0633\u0644\u064a\u0629 \u0639\u0646\u0627\u0628\u0629", "tourism": "theme_park"}}, {"type": "way", "id": 377885023, "nodes": [3812922610, 3812922611, 3812922612, 3812922613, 3812922614, 3812922615, 3812922616, 3812922617, 3812922618, 5516955025, 5516955026, 5516955024, 5516955023, 3812922619, 5516955022, 3812922610], "tags": {"addr:city": "Annaba", "addr:postcode": "23000", "name": "H\u00f4tel Sheraton", "name:ar": "\u0641\u0646\u062f\u0642 \u0634\u064a\u0631\u0627\u062a\u0648\u0646", "stars": "5", "tourism": "hotel"}}, {"type": "way", "id": 423725954, "nodes": [4232925332, 4232925333, 4232925334, 4232925335, 4232925336, 4232925337, 4232925338, 4232925339, 4232925340, 4232925341, 4232925342, 4232925343, 4232925344, 4232925345, 4232925346, 4232925347, 4232925348, 4232925349, 4232925350, 4232925351, 4232925352, 4232925353, 4232925354, 4232925355, 4232925356, 4232925357, 4232925358, 4232925359, 4232925360, 4232925361, 4232925362, 4232925332], "tags": {"name": "CRF DGSN Ain Achir", "name:ar": "\u0645\u0631\u0643\u0632 \u0627\u0644\u0631\u0627\u062d\u0629 \u0627\u0644\u0639\u0627\u0626\u0644\u064a \u0644\u0644\u0634\u0631\u0637\u0629 - \u0639\u064a\u0646 \u0639\u0634\u064a\u0631", "name:fr": "CRF DGSN Ain Achir", "tourism": "camp_site"}}, {"type": "way", "id": 425770889, "nodes": [4250811342, 4250811343, 4250811347, 4250811348, 4235893267, 4250811342], "tags": {"addr:city": "chetaibi", "addr:postcode": "23014", "tourism": "camp_site"}}, {"type": "way", "id": 426675188, "nodes": [4259470995, 4259470996, 4259470997, 4259470998, 4259470999, 4259471000, 4259471001, 4259471002, 4259471003, 4259471004, 4259471005, 4259471006, 4259471007, 4259471008, 4259471009, 4259471010, 4259471011, 4259471012, 4259471013, 4259471014, 4259471015, 4259471016, 4259471017, 4259471018, 4259471019, 4259471020, 4259471021, 4259471022, 4259471023, 4259471024, 4259471025, 4259471026, 4259471027, 4259471028, 4259471029, 4259471030, 4259471031, 4259471032, 4259471033, 4259471040, 4259471039, 4259471038, 4259471041, 4259471034, 4259471035, 4259471036, 4259471037, 4259470995], "tags": {"addr:city": "Sera\u00efdi", "building": "hotel", "email": "hotelmountazah@gmail.com", "name": "H\u00f4tel El Mountazah", "name:ar": "\u0641\u0646\u062f\u0642 \u0627\u0644\u0645\u0646\u062a\u0632\u0647", "phone": "+21338473559", "tourism": "hotel", "website": "http://groupe-htt.com"}}, {"type": "way", "id": 428036556, "nodes": [4271867440, 4271867441, 4271867442, 4271867443, 4271867440], "tags": {"building": "yes", "building:levels": "5", "name": "Hotel Le Majestic", "tourism": "hotel"}}, {"type": "way", "id": 617827965, "nodes": [1212053243, 5839961678, 5839961679, 5839961680, 5839961681, 5839961682, 5839961683, 5839961684, 5839961985, 5839961986, 5839961987, 5839961988, 5839961989, 5839961990, 5839962083, 5839962067, 5839962068, 5839961991, 5839961992, 5839961993, 5839961994, 5839961995, 5839961996, 5839961997, 5839961998, 1212053243], "tags": {"barrier": "wall", "name": "H\u00f4tel Sabri", "tourism": "hotel"}}]}